qeret/__init__.py
qeret/__main__.py
qeret/app/__init__.py
qeret/app/run.py
qeret-0.0.0.dev0.dist-info/licenses/LICENSE
qeret-0.0.0.dev0.dist-info/METADATA
qeret-0.0.0.dev0.dist-info/WHEEL
qeret-0.0.0.dev0.dist-info/top_level.txt
qeret-0.0.0.dev0.dist-info/RECORD
