Metadata-Version: 2.4
Name: qeret
Version: 0.0.0.dev0
Summary: A component-oriented build system for the C++ programming language
Author-email: "Oleg E. Vorobiov" <isnullxbh@gmail.com>
License-Expression: MIT
Project-URL: homepage, https://github.com/isnullxbh/Qeret
Project-URL: repository, https://github.com/isnullxbh/Qeret.git
Project-URL: issues, https://github.com/isnullxbh/Qeret/issues
Keywords: cpp,component,component-oriented,build system
License-File: LICENSE
Dynamic: license-file
